{
    "KINGDOM" : ["Name","Key","CMID"],
    "FAUNA" : ["Name","Key","CMID"],
    "PHYLUM" : ["Name","Key","CMID"],
    "CLASS" : ["Name","Key","CMID"],
    "ORDER" : ["Name","Key","CMID"],
    "FAMILY" : ["Name","Key","CMID"],
    "GENUS" : ["Name","Key","CMID"],
    "SPECIES" : ["Name","Key","CMID"],
    "SUBGENUS" : ["Name","Key","CMID"],
    "SUBSPECIES" : ["Name","Key","CMID"],
    "FEATURE" : ["Name","Key","CMID"],
    "ADM0" : ["Name","Key","CMID"],
    "ADM1" : ["Name","Key","CMID"],
    "ADM2" : ["Name","Key","CMID"],
    "ADM3" : ["Name","Key","CMID"],
    "DISTRICT" : ["Name","Key","CMID"],
    "REGION" : ["Name","Key","CMID"],
    "SITE" : ["Name","Key","CMID"],
    "STONE" : ["Name","Key","CMID"],
    "CULTURE" : ["Name","Key","CMID"],
    "CATEGORY" : ["Name","Key","CMID"],
    "CERAMIC" : ["Name","Key","CMID"],
    "CERAMIC_TYPE" : ["Name","Key","CMID"],
    "CERAMIC_WARE" : ["Name","Key","CMID"],
    "DATASET" : ["Name","DatasetCitation","CMID"],
    "PERIOD" : ["Name","Key","CMID"],
    "PROJECTILE_POINT" : ["Name","Key","CMID"],
    "PROJECTILE_POINT_CLUSTER" : ["Name","Key","CMID"],
    "PROJECTILE_POINT_TYPE" : ["Name","Key","CMID"],
    "VARIABLE" : ["Name","Key","CMID"]
}